ssh_api.py
ssh_api-1.0.0.dist-info/WHEEL
ssh_api-1.0.0.dist-info/METADATA
ssh_api-1.0.0.dist-info/RECORD
